{
  "Workflows": [
    {
      "Path": null,
      "SortBy": 0,
      "VariablesSectionElementsOrder": [],
      "ArgumentsSectionElementsOrder": null,
      "ConstantsSectionElementsOrder": null,
      "AddedNamespaces": null
    },
    {
      "Path": "Main.xaml",
      "SortBy": 0,
      "VariablesSectionElementsOrder": [
        "TransactionItem&StateMachine_1",
        "SystemException&StateMachine_1",
        "BusinessException&StateMachine_1",
        "TransactionNumber&StateMachine_1",
        "Config&StateMachine_1",
        "RetryNumber&StateMachine_1",
        "TransactionField2&StateMachine_1",
        "TransactionField1&StateMachine_1",
        "TransactionID&StateMachine_1",
        "dt_TransactionData&StateMachine_1",
        "ConsecutiveSystemExceptions&StateMachine_1",
        "ShouldStop&Sequence_25"
      ],
      "ArgumentsSectionElementsOrder": [
        "in_OrchestratorQueueName",
        "in_OrchestratorQueueFolder"
      ],
      "ConstantsSectionElementsOrder": null,
      "AddedNamespaces": null
    },
    {
      "Path": "System1/System1_NavigateTo_WI.xaml",
      "SortBy": 0,
      "VariablesSectionElementsOrder": [],
      "ArgumentsSectionElementsOrder": [
        "in_URL"
      ],
      "ConstantsSectionElementsOrder": null,
      "AddedNamespaces": null
    },
    {
      "Path": "System1/System1_ScrapeDataTable.xaml",
      "SortBy": 0,
      "VariablesSectionElementsOrder": [],
      "ArgumentsSectionElementsOrder": [
        "out_DataTale"
      ],
      "ConstantsSectionElementsOrder": null,
      "AddedNamespaces": null
    },
    {
      "Path": "System1/System1_FilterWIDataTable.xaml",
      "SortBy": 0,
      "VariablesSectionElementsOrder": [],
      "ArgumentsSectionElementsOrder": [
        "in_Type",
        "in_DataTable",
        "out_FileteredDataTable",
        "in_Status"
      ],
      "ConstantsSectionElementsOrder": null,
      "AddedNamespaces": null
    },
    {
      "Path": "PopulateQueue.xaml",
      "SortBy": 0,
      "VariablesSectionElementsOrder": [],
      "ArgumentsSectionElementsOrder": [
        "in_WI4Items",
        "in_QueueName"
      ],
      "ConstantsSectionElementsOrder": null,
      "AddedNamespaces": null
    },
    {
      "Path": "Framework/Process.xaml",
      "SortBy": 0,
      "VariablesSectionElementsOrder": [
        "PageIsActive&Sequence_1",
        "dt_WorkItems&Sequence_2"
      ],
      "ArgumentsSectionElementsOrder": [
        "in_TransactionItem",
        "in_Config"
      ],
      "ConstantsSectionElementsOrder": null,
      "AddedNamespaces": null
    }
  ]
}